servpy/__init__.py
servpy/servpy.py
servpy-1.0.0.dist-info/METADATA
servpy-1.0.0.dist-info/WHEEL
servpy-1.0.0.dist-info/top_level.txt
servpy-1.0.0.dist-info/RECORD
