Metadata-Version: 2.1
Name: servpy
Version: 1.0.0
Summary: ServPy is a Python library that allows you to bruteforce and find (ssh, ftp, windows) server in the internet by checking open ports
Author: Aymane Elhattab
Author-email: <aymane.elhattab.master@gmail.com>
License: UNKNOWN
Keywords: rdp,server,port-check,bruteforce
Platform: UNKNOWN
Classifier: Intended Audience :: Developers
Classifier: Programming Language :: Python :: 3
Classifier: Operating System :: Unix
Classifier: Operating System :: MacOS :: MacOS X
Classifier: Operating System :: Microsoft :: Windows
Requires-Dist: python-nmap
Requires-Dist: faker
